<?xml version="1.0" encoding="UTF-8"?>
<?xml-stylesheet type="text/xsl" href="../xslt/eMeasure.xsl"?>
<QualityMeasureDocument xmlns:xsi="http://www.w3.org/2001/XMLSchema-instance" xmlns="urn:hl7-org:v3">
         
      <!--
         **************************************************************   
         Measure Header Section
         **************************************************************
      --><typeId root="2.16.840.1.113883.1.3" extension="POQM_HD000001"/>
   <id root="c796ebcb-b03e-4ed7-99b2-b706561456ef"/>
   <code code="57024-2" codeSystem="2.16.840.1.113883.6.1" displayName="Health Quality Measure Document"/>
   <title>Colorectal Cancer Screening (NQF 0034)</title>
   <text>The percentage of adults 50-75 years of age who had appropriate screening for colorectal cancer.</text>
   <statusCode code="completed"/>
   <setId root="da479703-3931-40a0-909f-936ef106b1f1"/>
   <versionNumber value="1"/>
   <author typeCode="AUT">
      <assignedPerson classCode="ASSIGNED">
         <representedOrganization classCode="ORG" determinerCode="INSTANCE">
            <id root="2.16.840.1.113883.3.464"/>
            <name>National Committee for Quality Assurance</name>
            <contactParty classCode="CON" nullFlavor="UNK"/>
         </representedOrganization>
      </assignedPerson>
   </author>
   <custodian>
      <assignedPerson classCode="ASSIGNED">
         <representedOrganization classCode="ORG" determinerCode="INSTANCE">
            <id root="2.16.840.1.113883.3.464"/>
            <name>National Committee for Quality Assurance</name>
            <contactParty classCode="CON" nullFlavor="UNK"/>
         </representedOrganization>
      </assignedPerson>
   </custodian>
   <verifier typeCode="VRF">
      <assignedPerson classCode="ASSIGNED">
         <representedOrganization classCode="ORG" determinerCode="INSTANCE">
            <id root="2.16.840.1.113883.3.560"/>
            <name>National Quality Forum</name>
            <contactParty classCode="CON" nullFlavor="UNK"/>
         </representedOrganization>
      </assignedPerson>
   </verifier>
   <subjectOf>
      <measureAttribute>
         <code code="COPY" codeSystem="2.16.840.1.113883.5.4" displayName="Copyright"/>
         <value xsi:type="ED" mediaType="text/plain">© National Committee for Quality Assurance. All Rights Reserved</value>
      </measureAttribute>
   </subjectOf>
   <subjectOf>
      <measureAttribute>
         <code code="MSRSCORE" codeSystem="2.16.840.1.113883.5.4" displayName="Measure scoring"/>
         <value xsi:type="CD" code="PROPOR" codeSystem="2.16.840.1.113883.5.1063" displayName="Proportion"/>
      </measureAttribute>
   </subjectOf>
   <subjectOf>
      <measureAttribute>
         <code code="MSRTYPE" codeSystem="2.16.840.1.113883.5.4" displayName="Measure type"/>
         <value xsi:type="CD" code="PROCESS" codeSystem="2.16.840.1.113883.5.1063" displayName="Process"/>
      </measureAttribute>
   </subjectOf>
   <subjectOf>
      <measureAttribute>
         <code code="STRAT" codeSystem="2.16.840.1.113883.5.4" displayName="Stratification"/>
         <value xsi:type="ED" mediaType="text/plain">None</value>
      </measureAttribute>
   </subjectOf>
   <subjectOf>
      <measureAttribute>
         <code code="MSRADJ" codeSystem="2.16.840.1.113883.5.4" displayName="Risk Adjustment"/>
         <value xsi:type="ED" mediaType="text/plain">None</value>
      </measureAttribute>
   </subjectOf>
   <subjectOf>
      <measureAttribute>
         <code code="MSRAGG" codeSystem="2.16.840.1.113883.5.4" displayName="Data Aggregation"/>
         <value xsi:type="ED" mediaType="text/plain"/>
      </measureAttribute>
   </subjectOf>
   <subjectOf>
      <measureAttribute>
         <code code="RAT" codeSystem="2.16.840.1.113883.5.4" displayName="Rationale"/>
         <value xsi:type="ED" mediaType="text/plain"> This measure assesses the percentage of patients in a specific age demographic who receive appropriate screening for colorectal cancer. Colorectal cancer is the third leading cause of cancer-related deaths in the United States for both men and women, and was expected to be the primary cause of 49,920 deaths in 2009. In 2009, there were 106,100 new cases of colon cancer and 40,870 new cases of rectal cancer. Screening decreases mortality rates by detecting cancerous formations in the early and most curable stage; as a result, the mortality rate has been dropping for more than 20 years because of early identification of polyps for removal prior to disease onset, as well as other colorectal cancers. Screening is also fiscally responsible, with studies showing cost-savings of $40,000 per life-year gained. This measure facilitates efforts toward early detection of colorectal cancer and acceleration of treatment upon diagnosis. </value>
      </measureAttribute>
   </subjectOf>
   <subjectOf>
      <measureAttribute>
         <code code="CRS" codeSystem="2.16.840.1.113883.3.560" displayName="Clinical Recommendation Statement"/>
         <value xsi:type="ED" mediaType="text/plain"> The United States Preventive Services Task Force : 
[1]The USPSTF recommends screening for colorectal cancer using fecal occult blood testing, sigmoidoscopy, or colonoscopy in adults, beginning at age 50 years and continuing until age 75 years (A recommendation). 
[2]The USPSTF concludes that the evidence is insufficient to assess the benefits and harms of computed tomographic (CT) colonography and fecal DNA testing as screening modalities for colorectal cancer (I statement). 

The American Cancer Society, The American College of Radiology, and the U.S. Multi-Society Task Force on Colorectal Cancer: 
Tests that Detect Adenomatous Polyps and Cancer
[1]Colonoscopy (every 10 yrs) 
[2]Flexible sigmoidoscopy (every 5 yrs) 
[3]fecal occult blood tests (fecal occult blood test (FOBT)) (A) 
[4]Double contrast barium enema (DCBE) (every 5 yrs)
[5]Computed tomographic colonography (CTC) (every 5 years) 

Tests that Primarily Detect Cancer: 
[1]gfecal occult blood test (FOBT) with high sensitivity for cancer (annually) 
[2]FIT with high sensitivity for cancer (annually) 
[3]sDNA with high sensitivity for cancer (interval uncertain) 

Modalities not approved: 
[1]Single digital rectal examination fecal occult blood test (FOBT) has a poor sensitivity for CRC and should not be performed as a primary screening method (A) 
[2]Studies evaluating virtual colonoscopy and fecal DNA testing for CRC screening have yielded conflicting results and therefore cannot be recommended (A) </value>
      </measureAttribute>
   </subjectOf>
   <subjectOf>
      <measureAttribute>
         <code code="IDUR" codeSystem="2.16.840.1.113883.3.560" displayName="Improvement notation"/>
         <value xsi:type="ED" mediaType="text/plain">Higher score indicates better quality</value>
      </measureAttribute>
   </subjectOf>
   <subjectOf>
      <measureAttribute>
         <templateId root="2.16.840.1.113883.3.560.1.74"/>
         <id root="40ACB508-8ACA-40AB-9D65-562BCEA89A7A"/>
         <code code="MSRTP" displayName="Measurement period" codeSystem="2.16.840.1.113883.3.560"/>
         <value xsi:type="EXPR_PQ" value="12" unit="m">
            <expression mediaType="text/plain">measureEndDate - measureStartDate</expression>
         </value>
      </measureAttribute>
   </subjectOf>
   <subjectOf>
      <localVariableName>measureStartDate</localVariableName>
      <measureAttribute>
         <templateId root="2.16.840.1.113883.3.560.1.75"/>
         <id root="22CE90CA-CEE5-4143-9986-54E5309ED6D6"/>
         <code code="MSRSD" displayName="Measurement start date" codeSystem="2.16.840.1.113883.3.560"/>
         <value xsi:type="TS" value="00000101"/>
      </measureAttribute>
   </subjectOf>
   <subjectOf>
      <localVariableName>measureEndDate</localVariableName>
      <measureAttribute>
         <templateId root="2.16.840.1.113883.3.560.1.75"/>
         <id root="5A963515-F8BD-4450-A92C-4AC682A61D73"/>
         <code code="MSRED" displayName="Measurement end date" codeSystem="2.16.840.1.113883.3.560"/>
         <value xsi:type="TS" value="00001231"/>
      </measureAttribute>
   </subjectOf>
   <subjectOf>
      <measureAttribute>
         <code code="MSRMD" codeSystem="2.16.840.1.113883.3.560" displayName="Measurement duration"/>
         <value xsi:type="ED" mediaType="text/plain">12 month(s)</value>
      </measureAttribute>
   </subjectOf>
   <subjectOf>
      <measureAttribute>
         <code code="REF" codeSystem="2.16.840.1.113883.5.4" displayName="Reference"/>
         <value xsi:type="ED" mediaType="text/plain">Screening for Colorectal Cancer, Topic Page. October 2008. U.S. Preventive Services Task Force. Agency for Healthcare Research and Quality, Rockville, MD. http://www.ahrq.gov/clinic/uspstf/uspscolo.htm</value>
      </measureAttribute>
   </subjectOf>
   <subjectOf>
      <measureAttribute>
         <code code="REF" codeSystem="2.16.840.1.113883.5.4" displayName="Reference"/>
         <value xsi:type="ED" mediaType="text/plain">Levin, B. MD, et al. Screening and Surveillance for the Early Detection of Colorectal Cancer and Adenomatous Polyps, 2008: A Joint Guideline from the American Cancer Society, the US Multi-Society Task Force on Colorectal Cancer, and the American College of Radiology. CA Cancer J Clin 2008;58:00-00</value>
      </measureAttribute>
   </subjectOf>
   <subjectOf>
      <measureAttribute>
         <code code="DEF" codeSystem="2.16.840.1.113883.3.560" displayName="Definition"/>
         <value xsi:type="ED" mediaType="text/plain" nullFlavor="NI"/>
      </measureAttribute>
   </subjectOf>
   <subjectOf>
      <measureAttribute>
         <code code="GUIDE" codeSystem="2.16.840.1.113883.5.4" displayName="Guidance"/>
         <value xsi:type="ED" mediaType="text/plain"/>
      </measureAttribute>
   </subjectOf>
   <componentOf>
      <qualityMeasureSet classCode="ACT">
         <id root="B1EB421F-C28C-453C-8DEE-7C6EFE318EB1"/>
         <title>CLINICAL QUALITY MEASURE SET 2011-2012</title>
      </qualityMeasureSet>
   </componentOf>
         
      <!--
         **************************************************************   
         Population Criteria Section
         **************************************************************
      --><component typeCode="COMP">
      <section>
         <code code="57026-7" codeSystem="2.16.840.1.113883.6.1" displayName="Population criteria"/>
         <title>Population criteria</title>
         <text>
            <list>
               <item>
                  <content styleCode="Bold">Initial Patient Population =</content>
                  <list>
                     <item>AND: "Patient characteristic: birth date"  &gt;= 50 year(s) and &lt;= 74 year(s) starts before start of "Measurement period"</item>
                  </list>
               </item>
               <item>
                  <content styleCode="Bold">Denominator=</content>
                  <list>
                     <item>AND: "Initial Patient Population"</item>
                     <item>AND: "Encounter: encounter outpatient"  &lt;= 2 year(s) starts before or during "Measurement end date"</item>
                     <item>AND NOT:
                  <list>
                           <item>AND: "Procedure performed: total colectomy" starts before or during "Measurement end date"</item>
                        </list>
                     </item>
                  </list>
               </item>
               <item>
                  <content styleCode="Bold">Numerator =</content>
                  <list>
                     <item>AND: "Procedure performed: colonoscopy"  &lt;= 10 year(s) starts before or during "Measurement end date"</item>
                     <item>AND: "Procedure performed: flexible sigmoidoscopy"  &lt;= 5 year(s) starts before or during "Measurement end date"</item>
                     <item>AND: "Laboratory test performed: fecal occult blood test (FOBT)" during "Measurement period"</item>
                  </list>
               </item>
               <item>
                  <content styleCode="Bold">Exclusions =</content>
                  <list>
                     <item>OR: <list>
                           <item>OR: "Diagnosis active: colorectal cancer"</item>
                           <item>OR: "Diagnosis inactive: colorectal cancer"</item>
                           <item>OR: "Diagnosis resolved: colorectal cancer"</item>
                           <item> starts before or during "Measurement end date"</item>
                        </list>
                     </item>
                  </list>
               </item>
            </list>
         </text><!--
            **************************************************************   
            Population Criteria Section: population 
            **************************************************************
      -->
         <entry typeCode="DRIV">
            <observation classCode="OBS" moodCode="EVN.CRT" isCriterionInd="true">
               <id root="B2CCEC94-BDE6-4CE9-8184-3BD150192DF0"/>
               <code code="ASSERTION" codeSystem="2.16.840.1.113883.5.4"/>
               <value xsi:type="CD" code="IPP" codeSystem="2.16.840.1.113883.5.1063" codeSystemName="HL7 Observation Value" displayName="Initial Patient Population"/><!--  top and/or -->
               <sourceOf typeCode="PRCN">
                  <conjunctionCode code="AND"/>
                  <act classCode="ACT" moodCode="EVN" isCriterionInd="true"><!-- patient characteristic pattern -->
                     <templateId root="2.16.840.1.113883.3.560.1.25"/>
                     <id root="F9A89919-9074-43BD-81CE-483363EEDE75"/>
                     <code code="45970-1" displayName="Demographics" codeSystem="2.16.840.1.113883.6.1"/>
                     <sourceOf typeCode="COMP">
                        <observation classCode="OBS" moodCode="EVN" isCriterionInd="true">
                           <code code="2.16.840.1.113883.3.464.0001.14" displayName="birth date HL7 Code List"/>
                           <title>Patient characteristic: birth date</title>
                           <sourceOf typeCode="SBS">
                              <pauseQuantity xsi:type="IVL_PQ">
                                 <low value="50" unit="a" inclusive="true"/>
                                 <high value="74" unit="a" inclusive="true"/>
                              </pauseQuantity>
                              <observation classCode="OBS" moodCode="EVN">
                                 <id root="40ACB508-8ACA-40AB-9D65-562BCEA89A7A"/>
                                 <title>Measurement period</title>
                              </observation>
                           </sourceOf>
                        </observation>
                     </sourceOf>
                  </act>
               </sourceOf>
            </observation>
         </entry><!--
            **************************************************************   
            Population Criteria Section: denominator 
            **************************************************************
      -->
         <entry typeCode="DRIV">
            <observation classCode="OBS" moodCode="EVN.CRT" isCriterionInd="true">
               <id root="E809CCF0-6867-43F4-95B8-701CEEB35BE0"/>
               <code code="ASSERTION" codeSystem="2.16.840.1.113883.5.4"/>
               <value xsi:type="CD" code="DENOM" codeSystem="2.16.840.1.113883.5.1063" codeSystemName="HL7 Observation Value" displayName="Denominator"/><!--  top and/or -->
               <sourceOf typeCode="PRCN">
                  <conjunctionCode code="AND"/>
                  <observation classCode="OBS" moodCode="EVN" isCriterionInd="true">
                     <id root="B2CCEC94-BDE6-4CE9-8184-3BD150192DF0"/>
                     <title>Initial Patient Population</title>
                  </observation>
               </sourceOf>
               <sourceOf typeCode="PRCN">
                  <conjunctionCode code="AND"/>
                  <act classCode="ACT" moodCode="EVN" isCriterionInd="true"><!-- encounter pattern -->
                     <templateId root="2.16.840.1.113883.3.560.1.4"/>
                     <id root="723132CD-A821-4374-AB48-0B2BC0621C71"/>
                     <code code="46240-8" displayName="Encounter list" codeSystem="2.16.840.1.113883.6.1"/>
                     <sourceOf typeCode="COMP">
                        <encounter classCode="ENC" moodCode="EVN" isCriterionInd="true">
                           <code code="2.16.840.1.113883.3.464.0001.49" displayName="encounter outpatient Code List GROUPING"/>
                           <title>Encounter: encounter outpatient</title>
                           <sourceOf typeCode="EAS" inversionInd="true">
                              <pauseQuantity xsi:type="IVL_PQ">
                                 <high value="2" unit="a" inclusive="true"/>
                              </pauseQuantity>
                              <observation classCode="OBS" moodCode="EVN">
                                 <id root="5A963515-F8BD-4450-A92C-4AC682A61D73"/>
                                 <title>Measurement end date</title>
                              </observation>
                           </sourceOf>
                        </encounter>
                     </sourceOf>
                  </act>
               </sourceOf>
            </observation>
         </entry><!--
            **************************************************************   
            Population Criteria Section: numerator 
            **************************************************************
      -->
         <entry typeCode="DRIV">
            <observation classCode="OBS" moodCode="EVN.CRT" isCriterionInd="true">
               <id root="664987B9-F842-4277-971A-7237CA3DCDE4"/>
               <code code="ASSERTION" codeSystem="2.16.840.1.113883.5.4"/>
               <value xsi:type="CD" code="NUMER" codeSystem="2.16.840.1.113883.5.1063" codeSystemName="HL7 Observation Value" displayName="Numerator"/><!--  top and/or -->
               <sourceOf typeCode="PRCN">
                  <conjunctionCode code="AND"/>
                  <act classCode="ACT" moodCode="EVN" isCriterionInd="true"><!-- procedure performed pattern -->
                     <templateId root="2.16.840.1.113883.3.560.1.6"/>
                     <id root="E15D01C8-A66C-406A-B0E4-F65BAF936C64"/>
                     <code code="47519-4" displayName="Procedures" codeSystem="2.16.840.1.113883.6.1"/>
                     <sourceOf typeCode="COMP">
                        <procedure classCode="PROC" moodCode="EVN" isCriterionInd="true">
                           <code code="2.16.840.1.113883.3.464.0001.27" displayName="colonoscopy Code List GROUPING"/>
                           <title>Procedure performed: colonoscopy</title>
                           <sourceOf typeCode="EAS" inversionInd="true">
                              <pauseQuantity xsi:type="IVL_PQ">
                                 <high value="10" unit="a" inclusive="true"/>
                              </pauseQuantity>
                              <observation classCode="OBS" moodCode="EVN">
                                 <id root="5A963515-F8BD-4450-A92C-4AC682A61D73"/>
                                 <title>Measurement end date</title>
                              </observation>
                           </sourceOf>
                        </procedure>
                     </sourceOf>
                  </act>
               </sourceOf>
               <sourceOf typeCode="PRCN">
                  <conjunctionCode code="AND"/>
                  <act classCode="ACT" moodCode="EVN" isCriterionInd="true"><!-- procedure performed pattern -->
                     <templateId root="2.16.840.1.113883.3.560.1.6"/>
                     <id root="36A7F032-26A1-45CF-B609-7DA5B5F8911E"/>
                     <code code="47519-4" displayName="Procedures" codeSystem="2.16.840.1.113883.6.1"/>
                     <sourceOf typeCode="COMP">
                        <procedure classCode="PROC" moodCode="EVN" isCriterionInd="true">
                           <code code="2.16.840.1.113883.3.464.0001.57" displayName="flexible sigmoidoscopy Code List GROUPING"/>
                           <title>Procedure performed: flexible sigmoidoscopy</title>
                           <sourceOf typeCode="EAS" inversionInd="true">
                              <pauseQuantity xsi:type="IVL_PQ">
                                 <high value="5" unit="a" inclusive="true"/>
                              </pauseQuantity>
                              <observation classCode="OBS" moodCode="EVN">
                                 <id root="5A963515-F8BD-4450-A92C-4AC682A61D73"/>
                                 <title>Measurement end date</title>
                              </observation>
                           </sourceOf>
                        </procedure>
                     </sourceOf>
                  </act>
               </sourceOf>
               <sourceOf typeCode="PRCN">
                  <conjunctionCode code="AND"/>
                  <act classCode="ACT" moodCode="EVN" isCriterionInd="true"><!-- laboratory test performed pattern -->
                     <templateId root="2.16.840.1.113883.3.560.1.5"/>
                     <id root="FDDBFFB1-93CD-4A26-B817-3423545911B2"/>
                     <code code="30954-2" displayName="Results" codeSystem="2.16.840.1.113883.6.1"/>
                     <sourceOf typeCode="COMP">
                        <observation classCode="OBS" moodCode="EVN" isCriterionInd="true">
                           <code code="2.16.840.1.113883.3.464.0001.62" displayName="fecal occult blood test (FOBT) Code List GROUPING"/>
                           <title>Laboratory test performed: fecal occult blood test (FOBT)</title>
                           <statusCode code="completed"/>
                           <sourceOf typeCode="DURING">
                              <observation classCode="OBS" moodCode="EVN">
                                 <id root="40ACB508-8ACA-40AB-9D65-562BCEA89A7A"/>
                                 <title>Measurement period</title>
                              </observation>
                           </sourceOf>
                        </observation>
                     </sourceOf>
                  </act>
               </sourceOf>
            </observation>
         </entry><!--
            **************************************************************   
            Population Criteria Section: exclusions 
            **************************************************************
      -->
         <entry typeCode="DRIV">
            <observation classCode="OBS" moodCode="EVN.CRT" isCriterionInd="true" actionNegationInd="true">
               <id root="F070D21C-633E-4446-BC95-7D31FFF7F0E9"/>
               <code code="ASSERTION" codeSystem="2.16.840.1.113883.5.4"/>
               <value xsi:type="CD" code="DENOM" codeSystem="2.16.840.1.113883.5.1063" codeSystemName="HL7 Observation Value" displayName="Denominator"/><!--  top and/or -->
               <sourceOf typeCode="PRCN">
                  <conjunctionCode code="AND"/>
                  <act classCode="ACT" moodCode="EVN" isCriterionInd="true"><!-- procedure performed pattern -->
                     <templateId root="2.16.840.1.113883.3.560.1.6"/>
                     <id root="5DB72601-DB18-4D20-BA29-10A9D7DEA8D0"/>
                     <code code="47519-4" displayName="Procedures" codeSystem="2.16.840.1.113883.6.1"/>
                     <sourceOf typeCode="COMP">
                        <procedure classCode="PROC" moodCode="EVN" isCriterionInd="true">
                           <code code="2.16.840.1.113883.3.464.0001.128" displayName="total colectomy Code List GROUPING"/>
                           <title>Procedure performed: total colectomy</title>
                           <sourceOf typeCode="EAS" inversionInd="true">
                              <observation classCode="OBS" moodCode="EVN">
                                 <id root="5A963515-F8BD-4450-A92C-4AC682A61D73"/>
                                 <title>Measurement end date</title>
                              </observation>
                           </sourceOf>
                        </procedure>
                     </sourceOf>
                  </act>
               </sourceOf>
            </observation>
         </entry><!--
            **************************************************************   
            Population Criteria Section: exceptions 
            **************************************************************
      -->
         <entry typeCode="DRIV">
            <observation classCode="OBS" moodCode="EVN.CRT" isCriterionInd="true">
               <id root="A7F9EC9A-73CC-41C2-8991-B9F9AF29A45B"/>
               <code code="ASSERTION" codeSystem="2.16.840.1.113883.5.4"/>
               <value xsi:type="CD" code="DENEXCEP" codeSystem="2.16.840.1.113883.5.1063" codeSystemName="HL7 Observation Value" displayName="Denominator Exception"/><!--  top and/or -->
               <sourceOf typeCode="PRCN">
                  <conjunctionCode code="OR"/>
                  <act classCode="ACT" moodCode="EVN" isCriterionInd="true">
                     <sourceOf typeCode="PRCN">
                        <conjunctionCode code="OR"/>
                        <act classCode="ACT" moodCode="EVN" isCriterionInd="true"><!-- diagnosis active pattern -->
                           <templateId root="2.16.840.1.113883.3.560.1.2"/>
                           <id root="33BFB19B-A22E-4132-BF37-A6665300A7F0"/>
                           <code code="11450-4" displayName="Problem" codeSystem="2.16.840.1.113883.6.1"/>
                           <sourceOf typeCode="COMP">
                              <observation classCode="OBS" moodCode="EVN" isCriterionInd="true">
                                 <code code="55607006" codeSystem="2.16.840.1.113883.6.96" displayName="Problem"/>
                                 <title>Diagnosis active: colorectal cancer</title>
                                 <value xsi:type="CD" code="2.16.840.1.113883.3.464.0001.32" displayName="colorectal cancer Code List GROUPING"/>
                                 <sourceOf typeCode="REFR">
                                    <observation classCode="OBS" moodCode="EVN" isCriterionInd="true">
                                       <code code="33999-4" codeSystem="2.16.840.1.113883.6.1" displayName="Status"/>
                                       <value xsi:type="CD" code="55561003" displayName="active" codeSystem="2.16.840.1.113883.6.96"/>
                                    </observation>
                                 </sourceOf>
                              </observation>
                           </sourceOf>
                        </act>
                     </sourceOf>
                     <sourceOf typeCode="PRCN">
                        <conjunctionCode code="OR"/>
                        <act classCode="ACT" moodCode="EVN" isCriterionInd="true"><!-- diagnosis inactive pattern -->
                           <templateId root="2.16.840.1.113883.3.560.1.23"/>
                           <id root="7ED81A1E-4FD3-45AE-AD4D-697817029C0E"/>
                           <code code="11450-4" displayName="Problem" codeSystem="2.16.840.1.113883.6.1"/>
                           <sourceOf typeCode="COMP">
                              <observation classCode="OBS" moodCode="EVN" isCriterionInd="true">
                                 <code code="55607006" codeSystem="2.16.840.1.113883.6.96" displayName="Problem"/>
                                 <title>Diagnosis inactive: colorectal cancer</title>
                                 <value xsi:type="CD" code="2.16.840.1.113883.3.464.0001.32" displayName="colorectal cancer Code List GROUPING"/>
                                 <sourceOf typeCode="REFR">
                                    <observation classCode="OBS" moodCode="EVN" isCriterionInd="true">
                                       <code code="33999-4" codeSystem="2.16.840.1.113883.6.1" displayName="Status"/>
                                       <value xsi:type="CD" code="73425007" displayName="inactive" codeSystem="2.16.840.1.113883.6.96"/>
                                    </observation>
                                 </sourceOf>
                              </observation>
                           </sourceOf>
                        </act>
                     </sourceOf>
                     <sourceOf typeCode="PRCN">
                        <conjunctionCode code="OR"/>
                        <act classCode="ACT" moodCode="EVN" isCriterionInd="true"><!-- diagnosis resolved pattern -->
                           <templateId root="2.16.840.1.113883.3.560.1.24"/>
                           <id root="DA9C8FE1-305F-40D5-AA9C-13A7EED574A0"/>
                           <code code="11450-4" displayName="Problem" codeSystem="2.16.840.1.113883.6.1"/>
                           <sourceOf typeCode="COMP">
                              <observation classCode="OBS" moodCode="EVN" isCriterionInd="true">
                                 <code code="55607006" codeSystem="2.16.840.1.113883.6.96" displayName="Problem"/>
                                 <title>Diagnosis resolved: colorectal cancer</title>
                                 <value xsi:type="CD" code="2.16.840.1.113883.3.464.0001.32" displayName="colorectal cancer Code List GROUPING"/>
                                 <sourceOf typeCode="REFR">
                                    <observation classCode="OBS" moodCode="EVN" isCriterionInd="true">
                                       <code code="33999-4" codeSystem="2.16.840.1.113883.6.1" displayName="Status"/>
                                       <value xsi:type="CD" code="413322009" displayName="resolved" codeSystem="2.16.840.1.113883.6.96"/>
                                    </observation>
                                 </sourceOf>
                              </observation>
                           </sourceOf>
                        </act>
                     </sourceOf>
                     <sourceOf typeCode="EAS" inversionInd="true">
                        <observation classCode="OBS" moodCode="EVN" isCriterionInd="true">
                           <id root="5A963515-F8BD-4450-A92C-4AC682A61D73"/>
                           <title>Measurement end date</title>
                        </observation>
                     </sourceOf>
                  </act>
               </sourceOf>
            </observation>
         </entry>
      </section>
   </component>
         
      <!--
         ******************************************   
         Data Criteria Section
         ******************************************
      --><component typeCode="COMP">
      <section>
         <code code="57025-9" codeSystem="2.16.840.1.113883.6.1" displayName="Data criteria (QDS Data Elements)"/>
         <title>Data criteria (QDS Data Elements)</title>
         <text>
            <list>
               <item>
                  <content>"Diagnosis active: colorectal cancer"</content> using "colorectal cancer Code List GROUPING (2.16.840.1.113883.3.464.0001.32)"</item>
               <item>
                  <content>"Diagnosis inactive: colorectal cancer"</content> using "colorectal cancer Code List GROUPING (2.16.840.1.113883.3.464.0001.32)"</item>
               <item>
                  <content>"Diagnosis resolved: colorectal cancer"</content> using "colorectal cancer Code List GROUPING (2.16.840.1.113883.3.464.0001.32)"</item>
               <item>
                  <content>"Encounter: encounter outpatient"</content> using "encounter outpatient Code List GROUPING (2.16.840.1.113883.3.464.0001.49)"</item>
               <item>
                  <content>"Laboratory test performed: fecal occult blood test (FOBT)"</content> using "fecal occult blood test (FOBT) Code List GROUPING (2.16.840.1.113883.3.464.0001.62)"</item>
               <item>
                  <content>"Patient characteristic: birth date" (age)</content> using "birth date HL7 Code List (2.16.840.1.113883.3.464.0001.14)"</item>
               <item>
                  <content>"Procedure performed: colonoscopy"</content> using "colonoscopy Code List GROUPING (2.16.840.1.113883.3.464.0001.27)"</item>
               <item>
                  <content>"Procedure performed: flexible sigmoidoscopy"</content> using "flexible sigmoidoscopy Code List GROUPING (2.16.840.1.113883.3.464.0001.57)"</item>
               <item>
                  <content>"Procedure performed: total colectomy"</content> using "total colectomy Code List GROUPING (2.16.840.1.113883.3.464.0001.128)"</item>
            </list>
         </text>
         <entry typeCode="DRIV">
            <act classCode="ACT" moodCode="EVN" isCriterionInd="true"><!-- patient characteristic pattern -->
               <templateId root="2.16.840.1.113883.3.560.1.25"/>
               <id root="F9A89919-9074-43BD-81CE-483363EEDE75"/>
               <code code="45970-1" displayName="Demographics" codeSystem="2.16.840.1.113883.6.1"/>
               <sourceOf typeCode="COMP">
                  <observation classCode="OBS" moodCode="EVN" isCriterionInd="true">
                     <code code="2.16.840.1.113883.3.464.0001.14" displayName="birth date HL7 Code List"/>
                     <title>Patient characteristic: birth date</title>
                  </observation>
               </sourceOf>
            </act>
         </entry>
         <entry typeCode="DRIV">
            <act classCode="ACT" moodCode="EVN" isCriterionInd="true"><!-- procedure performed pattern -->
               <templateId root="2.16.840.1.113883.3.560.1.6"/>
               <id root="E15D01C8-A66C-406A-B0E4-F65BAF936C64"/>
               <code code="47519-4" displayName="Procedures" codeSystem="2.16.840.1.113883.6.1"/>
               <sourceOf typeCode="COMP">
                  <procedure classCode="PROC" moodCode="EVN" isCriterionInd="true">
                     <code code="2.16.840.1.113883.3.464.0001.27" displayName="colonoscopy Code List GROUPING"/>
                     <title>Procedure performed: colonoscopy</title>
                  </procedure>
               </sourceOf>
            </act>
         </entry>
         <entry typeCode="DRIV">
            <act classCode="ACT" moodCode="EVN" isCriterionInd="true"><!-- diagnosis active pattern -->
               <templateId root="2.16.840.1.113883.3.560.1.2"/>
               <id root="33BFB19B-A22E-4132-BF37-A6665300A7F0"/>
               <code code="11450-4" displayName="Problem" codeSystem="2.16.840.1.113883.6.1"/>
               <sourceOf typeCode="COMP">
                  <observation classCode="OBS" moodCode="EVN" isCriterionInd="true">
                     <code code="55607006" codeSystem="2.16.840.1.113883.6.96" displayName="Problem"/>
                     <title>Diagnosis active: colorectal cancer</title>
                     <value xsi:type="CD" code="2.16.840.1.113883.3.464.0001.32" displayName="colorectal cancer Code List GROUPING"/>
                     <sourceOf typeCode="REFR">
                        <observation classCode="OBS" moodCode="EVN" isCriterionInd="true">
                           <code code="33999-4" codeSystem="2.16.840.1.113883.6.1" displayName="Status"/>
                           <value xsi:type="CD" code="55561003" displayName="active" codeSystem="2.16.840.1.113883.6.96"/>
                        </observation>
                     </sourceOf>
                  </observation>
               </sourceOf>
            </act>
         </entry>
         <entry typeCode="DRIV">
            <act classCode="ACT" moodCode="EVN" isCriterionInd="true"><!-- diagnosis inactive pattern -->
               <templateId root="2.16.840.1.113883.3.560.1.23"/>
               <id root="7ED81A1E-4FD3-45AE-AD4D-697817029C0E"/>
               <code code="11450-4" displayName="Problem" codeSystem="2.16.840.1.113883.6.1"/>
               <sourceOf typeCode="COMP">
                  <observation classCode="OBS" moodCode="EVN" isCriterionInd="true">
                     <code code="55607006" codeSystem="2.16.840.1.113883.6.96" displayName="Problem"/>
                     <title>Diagnosis inactive: colorectal cancer</title>
                     <value xsi:type="CD" code="2.16.840.1.113883.3.464.0001.32" displayName="colorectal cancer Code List GROUPING"/>
                     <sourceOf typeCode="REFR">
                        <observation classCode="OBS" moodCode="EVN" isCriterionInd="true">
                           <code code="33999-4" codeSystem="2.16.840.1.113883.6.1" displayName="Status"/>
                           <value xsi:type="CD" code="73425007" displayName="inactive" codeSystem="2.16.840.1.113883.6.96"/>
                        </observation>
                     </sourceOf>
                  </observation>
               </sourceOf>
            </act>
         </entry>
         <entry typeCode="DRIV">
            <act classCode="ACT" moodCode="EVN" isCriterionInd="true"><!-- diagnosis resolved pattern -->
               <templateId root="2.16.840.1.113883.3.560.1.24"/>
               <id root="DA9C8FE1-305F-40D5-AA9C-13A7EED574A0"/>
               <code code="11450-4" displayName="Problem" codeSystem="2.16.840.1.113883.6.1"/>
               <sourceOf typeCode="COMP">
                  <observation classCode="OBS" moodCode="EVN" isCriterionInd="true">
                     <code code="55607006" codeSystem="2.16.840.1.113883.6.96" displayName="Problem"/>
                     <title>Diagnosis resolved: colorectal cancer</title>
                     <value xsi:type="CD" code="2.16.840.1.113883.3.464.0001.32" displayName="colorectal cancer Code List GROUPING"/>
                     <sourceOf typeCode="REFR">
                        <observation classCode="OBS" moodCode="EVN" isCriterionInd="true">
                           <code code="33999-4" codeSystem="2.16.840.1.113883.6.1" displayName="Status"/>
                           <value xsi:type="CD" code="413322009" displayName="resolved" codeSystem="2.16.840.1.113883.6.96"/>
                        </observation>
                     </sourceOf>
                  </observation>
               </sourceOf>
            </act>
         </entry>
         <entry typeCode="DRIV">
            <act classCode="ACT" moodCode="EVN" isCriterionInd="true"><!-- encounter pattern -->
               <templateId root="2.16.840.1.113883.3.560.1.4"/>
               <id root="723132CD-A821-4374-AB48-0B2BC0621C71"/>
               <code code="46240-8" displayName="Encounter list" codeSystem="2.16.840.1.113883.6.1"/>
               <sourceOf typeCode="COMP">
                  <encounter classCode="ENC" moodCode="EVN" isCriterionInd="true">
                     <code code="2.16.840.1.113883.3.464.0001.49" displayName="encounter outpatient Code List GROUPING"/>
                     <title>Encounter: encounter outpatient</title>
                  </encounter>
               </sourceOf>
            </act>
         </entry>
         <entry typeCode="DRIV">
            <act classCode="ACT" moodCode="EVN" isCriterionInd="true"><!-- procedure performed pattern -->
               <templateId root="2.16.840.1.113883.3.560.1.6"/>
               <id root="36A7F032-26A1-45CF-B609-7DA5B5F8911E"/>
               <code code="47519-4" displayName="Procedures" codeSystem="2.16.840.1.113883.6.1"/>
               <sourceOf typeCode="COMP">
                  <procedure classCode="PROC" moodCode="EVN" isCriterionInd="true">
                     <code code="2.16.840.1.113883.3.464.0001.57" displayName="flexible sigmoidoscopy Code List GROUPING"/>
                     <title>Procedure performed: flexible sigmoidoscopy</title>
                  </procedure>
               </sourceOf>
            </act>
         </entry>
         <entry typeCode="DRIV">
            <act classCode="ACT" moodCode="EVN" isCriterionInd="true"><!-- laboratory test performed pattern -->
               <templateId root="2.16.840.1.113883.3.560.1.5"/>
               <id root="FDDBFFB1-93CD-4A26-B817-3423545911B2"/>
               <code code="30954-2" displayName="Results" codeSystem="2.16.840.1.113883.6.1"/>
               <sourceOf typeCode="COMP">
                  <observation classCode="OBS" moodCode="EVN" isCriterionInd="true">
                     <code code="2.16.840.1.113883.3.464.0001.62" displayName="fecal occult blood test (FOBT) Code List GROUPING"/>
                     <title>Laboratory test performed: fecal occult blood test (FOBT)</title>
                     <statusCode code="completed"/>
                  </observation>
               </sourceOf>
            </act>
         </entry>
         <entry typeCode="DRIV">
            <act classCode="ACT" moodCode="EVN" isCriterionInd="true"><!-- procedure performed pattern -->
               <templateId root="2.16.840.1.113883.3.560.1.6"/>
               <id root="5DB72601-DB18-4D20-BA29-10A9D7DEA8D0"/>
               <code code="47519-4" displayName="Procedures" codeSystem="2.16.840.1.113883.6.1"/>
               <sourceOf typeCode="COMP">
                  <procedure classCode="PROC" moodCode="EVN" isCriterionInd="true">
                     <code code="2.16.840.1.113883.3.464.0001.128" displayName="total colectomy Code List GROUPING"/>
                     <title>Procedure performed: total colectomy</title>
                  </procedure>
               </sourceOf>
            </act>
         </entry>
      </section>
   </component>
   <component typeCode="COMP">
      <section>
         <title>Summary Calculation</title>
         <text>
            <content>Calculation is generic to all measures:</content>
            <list>
               <item>Calculate the final denominator by adding all that meet denominator criteria.</item>
               <item>Subtract from the final denominator all that do not meet numerator criteria yet also meet exclusion criteria.  Note some measures do not have exclusion criteria.</item>
               <item>The performance calculation is based on the "Measure scoring" from header information above:
					        	<list>
                     <item>For "Proportion" measures, the calculation is the number meeting numerator criteria divided by the final denominator.</item>
                     <item>For "Ratio" and "Continuous Variable" measures, follow the calculation instructions in the Data Aggregation header information above, if present.</item>
                  </list>
               </item>
               <item>For measures with multiple denominators, repeat this process for each denominator and report each result separately.</item>
               <item>For measures with multiple patient populations, repeat this process for each patient population and report each result separately.</item>
               <item>For measures with multiple numerators, calculate each numerator separately within each population using the paired exclusion.</item>
            </list>
         </text>
      </section>
   </component>
</QualityMeasureDocument>